{
  "result": {
    "records": [
      {
        "_id": 217,
        "Date": "2025-08-05",
        "Day": "Tuesday",
        "Subuh": "5:46",
        "Syuruk": "7:06",
        "Zohor": "1:12",
        "Asar": "4:33",
        "Maghrib": "7:16",
        "Isyak": "8:29"
      },
      {
        "_id": 218,
        "Date": "2025-08-06",
        "Day": "Wednesday",
        "Subuh": "5:46",
        "Syuruk": "7:06",
        "Zohor": "1:12",
        "Asar": "4:33",
        "Maghrib": "7:16",
        "Isyak": "8:28"
      },
      {
        "_id": 236,
        "Date": "2025-08-24",
        "Day": "Sunday",
        "Subuh": "5:45",
        "Syuruk": "7:03",
        "Zohor": "1:09",
        "Asar": "4:24",
        "Maghrib": "7:12",
        "Isyak": "8:22"
      },
      {
        "_id": 268,
        "Date": "2025-09-25",
        "Day": "Thursday",
        "Subuh": "5:37",
        "Syuruk": "6:54",
        "Zohor": "12:58",
        "Asar": "4:01",
        "Maghrib": "7:01",
        "Isyak": "8:09"
      },
      {
        "_id": 269,
        "Date": "2025-09-26",
        "Day": "Friday",
        "Subuh": "5:37",
        "Syuruk": "6:54",
        "Zohor": "12:58",
        "Asar": "4:01",
        "Maghrib": "7:00",
        "Isyak": "8:09"
      },
      {
        "_id": 274,
        "Date": "2025-10-01",
        "Day": "Wednesday",
        "Subuh": "5:35",
        "Syuruk": "6:52",
        "Zohor": "12:56",
        "Asar": "4:03",
        "Maghrib": "6:58",
        "Isyak": "8:07"
      }
    ]
  },
  "last_updated": "2025-10-01T20:07:23+08:00",
  "last_fetched_date": "2025-10-01"
}